odoo10_addon_l10n_fr_das2-10.0.1.0.0.99.dev20-py3.8-nspkg.pth
odoo/addons/l10n_fr_das2/README.rst
odoo/addons/l10n_fr_das2/__init__.py
odoo/addons/l10n_fr_das2/__manifest__.py
odoo/addons/l10n_fr_das2/demo/demo.xml
odoo/addons/l10n_fr_das2/models/__init__.py
odoo/addons/l10n_fr_das2/models/account_config_settings.py
odoo/addons/l10n_fr_das2/models/company.py
odoo/addons/l10n_fr_das2/models/l10n_fr_das2.py
odoo/addons/l10n_fr_das2/models/partner.py
odoo/addons/l10n_fr_das2/readme/CONFIGURE.rst
odoo/addons/l10n_fr_das2/readme/CONTRIBUTORS.rst
odoo/addons/l10n_fr_das2/readme/DESCRIPTION.rst
odoo/addons/l10n_fr_das2/readme/USAGE.rst
odoo/addons/l10n_fr_das2/security/das2_security.xml
odoo/addons/l10n_fr_das2/security/ir.model.access.csv
odoo/addons/l10n_fr_das2/static/description/icon.png
odoo/addons/l10n_fr_das2/static/description/index.html
odoo/addons/l10n_fr_das2/views/account_config_settings.xml
odoo/addons/l10n_fr_das2/views/l10n_fr_das2.xml
odoo/addons/l10n_fr_das2/views/partner.xml
odoo10_addon_l10n_fr_das2-10.0.1.0.0.99.dev20.dist-info/METADATA
odoo10_addon_l10n_fr_das2-10.0.1.0.0.99.dev20.dist-info/WHEEL
odoo10_addon_l10n_fr_das2-10.0.1.0.0.99.dev20.dist-info/namespace_packages.txt
odoo10_addon_l10n_fr_das2-10.0.1.0.0.99.dev20.dist-info/top_level.txt
odoo10_addon_l10n_fr_das2-10.0.1.0.0.99.dev20.dist-info/RECORD
